[
    {
        "skill": "HTML",
        "progress": 90,
        "logo": "/img/HTML5.png",
        "description": "Craft semantic, accessible, and SEO-friendly web structures using modern HTML5 standards.",
        "years": 2,
        "skillType": "Markup Language",
        "className": "col-span-2 row-span-1"
    },
    {
        "skill": "CSS",
        "progress": 95,
        "logo": "/img/CSS3.png",
        "description": "Design responsive, visually appealing websites with advanced layouts, animations, and transitions.",
        "years": 2,
        "skillType": "Styling Language",
        "className": "col-span-1 row-span-2"
    },
    {
        "skill": "JavaScript",
        "progress": 65,
        "logo": "/img/JS.png",
        "description": "Develop interactive, dynamic web applications with client-side scripting and functionality.",
        "years": 1,
        "skillType": "Programming Language",
        "className": "col-span-1 row-span-1"
    },
    {
        "skill": "PHP",
        "progress": 70,
        "logo": "/img/PHP.png",
        "description": "Create dynamic server-side web applications and work with databases such as MySQL.",
        "years": 0.5,
        "skillType": "Server-side Language",
        "className": "col-span-2 row-span-1"
    },
    {
        "skill": "Next.js",
        "progress": 40,
        "logo": "/img/Nextjs.png",
        "description": "Build performant, server-rendered React applications with static-site generation and SSR.",
        "years": 0.25,
        "skillType": "React Framework",
        "className": "col-span-1 row-span-1"
    },
    {
        "skill": "Figma",
        "progress": 80,
        "logo": "/img/Figma.png",
        "description": "Design intuitive and engaging user interfaces with collaborative prototyping tools.",
        "years": 2.5,
        "skillType": "UI/UX Design Tool",
        "className": "col-span-2 row-span-2"
    },
    {
        "skill": "TypeScript",
        "progress": 20,
        "logo": "/img/TypeScript.png",
        "description": "Leverage strong typing in JavaScript to build scalable and maintainable applications.",
        "years": 0.25,
        "skillType": "Superset of JavaScript",
        "className": "col-span-1 row-span-1"
    },
    {
        "skill": "WordPress",
        "progress": 20,
        "logo": "/img/WordPress.png",
        "description": "Develop custom themes and fully functional WordPress websites with PHP and MySQL.",
        "years": 0.25,
        "skillType": "Content Management System",
        "className": "col-span-1 row-span-1"
    }
]
